chtoolsetext/__init__.py
chtoolsetext/_extras.cpython-39-darwin.so
chtoolsetext/other.py
clickhouse_toolset_extras-0.16.dev0.dist-info/LICENSE
clickhouse_toolset_extras-0.16.dev0.dist-info/METADATA
clickhouse_toolset_extras-0.16.dev0.dist-info/WHEEL
clickhouse_toolset_extras-0.16.dev0.dist-info/top_level.txt
clickhouse_toolset_extras-0.16.dev0.dist-info/RECORD
