Metadata-Version: 2.1
Name: clickhouse-toolset-extras
Version: 0.16.dev0
Summary: UNKNOWN
Home-page: https://gitlab.com/tinybird/clickhouse-toolset
Author: Tinybird.co
Author-email: support@tinybird.co
License: UNKNOWN
Platform: UNKNOWN
Requires-Python: >=3.7, <3.11
License-File: LICENSE
Provides-Extra: test
Requires-Dist: pytest ; extra == 'test'
